new_tools/__init__.py
new_tools/media/__init__.py
new_tools/media/image.py
new_tools/media/video.py
new_tools/string/__init__.py
new_tools/string/check_type.py
new_tools-0.0.10.dist-info/LICENSE
new_tools-0.0.10.dist-info/METADATA
new_tools-0.0.10.dist-info/WHEEL
new_tools-0.0.10.dist-info/top_level.txt
new_tools-0.0.10.dist-info/RECORD
