Metadata-Version: 2.1
Name: new-tools
Version: 0.0.10
Summary: Multiple tools
Home-page: https://github.com/Michael07220823/new_tools.git
Author: Overcomer
Author-email: michael31703@gmail.com
License: MIT License
Keywords: tools
Platform: UNKNOWN
Classifier: Programming Language :: Python :: 3
Classifier: License :: OSI Approved :: MIT License
Classifier: Operating System :: OS Independent
License-File: LICENSE
Requires-Dist: opencv-python
Requires-Dist: numpy
